wonder_pkg/__init__.py
wonder_pkg_walerydewelow-0.0.1.dist-info/LICENSE
wonder_pkg_walerydewelow-0.0.1.dist-info/METADATA
wonder_pkg_walerydewelow-0.0.1.dist-info/WHEEL
wonder_pkg_walerydewelow-0.0.1.dist-info/top_level.txt
wonder_pkg_walerydewelow-0.0.1.dist-info/RECORD
